criptografia/__init__.py
criptografia/demo.py
Criptografia-1.0.0.dist-info/METADATA
Criptografia-1.0.0.dist-info/WHEEL
Criptografia-1.0.0.dist-info/top_level.txt
Criptografia-1.0.0.dist-info/RECORD
