Metadata-Version: 2.1
Name: Criptografia
Version: 1.0.0
Summary: Um pacote para decifrar, cifrar e encriptar mensagens usando matrizes de permutação
Home-page: https://github.com/eriksoaress/Criptografia
Author: Fernando Santos e Erik Oliveira
Author-email: fervsantos3000@gmail.com
License: UNKNOWN
Platform: UNKNOWN
Classifier: License :: OSI Approved :: MIT License
Classifier: Development Status :: 5 - Production/Stable
Classifier: License :: OSI Approved :: MIT License
Classifier: Programming Language :: Python :: 3
Classifier: Programming Language :: Python :: 3.6
Classifier: Programming Language :: Python :: 3.7
Classifier: Programming Language :: Python :: 3.8
Classifier: Programming Language :: Python :: 3.9
Classifier: Programming Language :: Python :: 3.10
Classifier: Operating System :: OS Independent
